statistics_toolkit_cli/__init__.py
statistics_toolkit_cli/cli.py
statistics_toolkit_cli/core/__init__.py
statistics_toolkit_cli/core/confidence.py
statistics_toolkit_cli/core/descriptive.py
statistics_toolkit_cli/core/hypothesis.py
statistics_toolkit_cli/core/probability.py
statistics_toolkit_cli/core/regression.py
statistics_toolkit_cli/core/visualization.py
statistics_toolkit_cli/utils/__init__.py
statistics_toolkit_cli/utils/data_manager.py
statistics_toolkit_cli-1.0.0.dist-info/licenses/LICENSE
statistics_toolkit_cli-1.0.0.dist-info/METADATA
statistics_toolkit_cli-1.0.0.dist-info/WHEEL
statistics_toolkit_cli-1.0.0.dist-info/entry_points.txt
statistics_toolkit_cli-1.0.0.dist-info/top_level.txt
statistics_toolkit_cli-1.0.0.dist-info/RECORD
