Metadata-Version: 2.4
Name: statistics-toolkit-cli
Version: 1.0.0
Summary: A comprehensive command-line statistics learning tool with step-by-step explanations
Author-email: Connor O'Dea <connorodea@users.noreply.github.com>
Maintainer-email: Connor O'Dea <connorodea@users.noreply.github.com>
License: MIT
Project-URL: Homepage, https://github.com/connorodea/statistics-toolkit-cli
Project-URL: Bug Reports, https://github.com/connorodea/statistics-toolkit-cli/issues
Project-URL: Source, https://github.com/connorodea/statistics-toolkit-cli
Project-URL: Documentation, https://github.com/connorodea/statistics-toolkit-cli#readme
Keywords: statistics,education,cli,mathematics,learning,data-analysis
Classifier: Development Status :: 4 - Beta
Classifier: Intended Audience :: Education
Classifier: Intended Audience :: Science/Research
Classifier: License :: OSI Approved :: MIT License
Classifier: Operating System :: OS Independent
Classifier: Programming Language :: Python :: 3
Classifier: Programming Language :: Python :: 3.8
Classifier: Programming Language :: Python :: 3.9
Classifier: Programming Language :: Python :: 3.10
Classifier: Programming Language :: Python :: 3.11
Classifier: Programming Language :: Python :: 3.12
Classifier: Topic :: Scientific/Engineering :: Mathematics
Classifier: Topic :: Education
Classifier: Topic :: Software Development :: Libraries :: Python Modules
Classifier: Environment :: Console
Requires-Python: >=3.8
License-File: LICENSE
Requires-Dist: numpy>=1.21.0
Requires-Dist: pandas>=1.3.0
Requires-Dist: scipy>=1.7.0
Requires-Dist: matplotlib>=3.4.0
Provides-Extra: dev
Requires-Dist: pytest>=6.0; extra == "dev"
Requires-Dist: pytest-cov; extra == "dev"
Requires-Dist: black; extra == "dev"
Requires-Dist: flake8; extra == "dev"
Requires-Dist: mypy; extra == "dev"
Requires-Dist: build; extra == "dev"
Requires-Dist: twine; extra == "dev"
Dynamic: license-file
